vkstest/__init__.py
vkstest/api.py
vkstest/cli.py
vkstest-1.1.16.dist-info/LICENSE
vkstest-1.1.16.dist-info/METADATA
vkstest-1.1.16.dist-info/WHEEL
vkstest-1.1.16.dist-info/entry_points.txt
vkstest-1.1.16.dist-info/top_level.txt
vkstest-1.1.16.dist-info/RECORD
