Metadata-Version: 2.1
Name: vkstest
Version: 1.1.16
Summary: Command line Merrian-Webster Utility
Author-email: Vikash Kumar Shrivastva <vkshrivastva@yahoo.co.in>
Maintainer-email: Vikash Kumar Shrivastva <vkshrivastva@yahoo.co.in>
License: Copyright (c) 2018 The Python Packaging Authority
Project-URL: Homepage, https://gitlab.com/assignment7233743/vkstest
Requires-Python: >=3.8
License-File: LICENSE
